dbtdocgen_rutryk/__init__.py
dbtdocgen_rutryk/dbtdocgen.py
dbtdocgen_rutryk-0.0.8.dist-info/LICENSE
dbtdocgen_rutryk-0.0.8.dist-info/METADATA
dbtdocgen_rutryk-0.0.8.dist-info/WHEEL
dbtdocgen_rutryk-0.0.8.dist-info/entry_points.txt
dbtdocgen_rutryk-0.0.8.dist-info/top_level.txt
dbtdocgen_rutryk-0.0.8.dist-info/RECORD
