Metadata-Version: 2.1
Name: dbtdocgen-rutryk
Version: 0.0.8
Summary: dbt doc generator
Author-email: R K Lalli <rubjitkaurlalli@gmail.com>
Classifier: Programming Language :: Python :: 3
Classifier: License :: OSI Approved :: MIT License
Classifier: Operating System :: OS Independent
Requires-Python: >=3.7
License-File: LICENSE
Requires-Dist: click
